py2ts/__init__.py
py2ts/__init__.pyi
py2ts/exceptions.py
py2ts/exceptions.pyi
py2ts/generate_service_registry.py
py2ts/generate_service_registry.pyi
py2ts/python2ts.py
py2ts/python2ts.pyi
py2ts-0.0.6.dist-info/LICENSE
py2ts-0.0.6.dist-info/METADATA
py2ts-0.0.6.dist-info/WHEEL
py2ts-0.0.6.dist-info/top_level.txt
py2ts-0.0.6.dist-info/RECORD
